mydy/Constants.py
mydy/Containers.py
mydy/Events.py
mydy/FileIO.py
mydy/Util.py
mydy/__init__.py
mydy-0.0.3.data/scripts/mididump.py
mydy-0.0.3.data/scripts/mididumphw.py
mydy-0.0.3.data/scripts/midiplay.py
mydy-0.0.3.dist-info/LICENSE.txt
mydy-0.0.3.dist-info/METADATA
mydy-0.0.3.dist-info/RECORD
mydy-0.0.3.dist-info/WHEEL
mydy-0.0.3.dist-info/top_level.txt
