Metadata-Version: 2.1
Name: mydy
Version: 0.0.3
Summary: Vectorized Python MIDI IO
Home-page: https://gitlab.com/phrz/mydy
Author: James Wenzel
Author-email: jameswenzel@berkeley.edu
License: UNKNOWN
Platform: UNKNOWN
